lark_helper_mcp/__init__.py
lark_helper_mcp/__main__.py
lark_helper_mcp/config.py
lark_helper_mcp/server.py
lark_helper_mcp-0.1.0.dist-info/licenses/LICENSE
lark_helper_mcp-0.1.0.dist-info/METADATA
lark_helper_mcp-0.1.0.dist-info/WHEEL
lark_helper_mcp-0.1.0.dist-info/entry_points.txt
lark_helper_mcp-0.1.0.dist-info/top_level.txt
lark_helper_mcp-0.1.0.dist-info/RECORD
