Metadata-Version: 2.4
Name: lark-helper-mcp
Version: 0.1.0
Summary: A Model Context Protocol (MCP) server for Lark (Feishu) integration
Author: philoveritas
License-Expression: MIT
Project-URL: Homepage, https://github.com/philoveritas/lark-helper-mcp
Project-URL: Repository, https://github.com/philoveritas/lark-helper-mcp
Project-URL: Issues, https://github.com/philoveritas/lark-helper-mcp/issues
Keywords: mcp,lark,feishu,claude,ai
Classifier: Development Status :: 3 - Alpha
Classifier: Intended Audience :: Developers
Classifier: Operating System :: OS Independent
Classifier: Programming Language :: Python :: 3
Classifier: Programming Language :: Python :: 3.12
Classifier: Topic :: Communications :: Chat
Classifier: Topic :: Software Development :: Libraries :: Python Modules
Requires-Python: >=3.12
License-File: LICENSE
Requires-Dist: lark-helper==0.1.0.dev15
Requires-Dist: mcp[cli]>=1.13.1
Dynamic: license-file
